[
  {
    "model": "account.emailaddress",
    "pk": 1,
    "fields": {
      "user": 1,
      "email": "aaron_sanchez@example.com",
      "verified": true,
      "primary": true
    }
  },
  {
    "model": "account.emailaddress",
    "pk": 2,
    "fields": {
      "user": 2,
      "email": "abigail_thomas@example.com",
      "verified": true,
      "primary": true
    }
  },
  {
    "model": "account.emailaddress",
    "pk": 3,
    "fields": {
      "user": 3,
      "email": "alexis_cooper@example.com",
      "verified": true,
      "primary": true
    }
  },
  {
    "model": "account.emailaddress",
    "pk": 4,
    "fields": {
      "user": 4,
      "email": "aurora_morales@example.com",
      "verified": true,
      "primary": true
    }
  },
  {
    "model": "account.emailaddress",
    "pk": 5,
    "fields": {
      "user": 5,
      "email": "bailey_ramirez@example.com",
      "verified": true,
      "primary": true
    }
  },
  {
    "model": "account.emailaddress",
    "pk": 6,
    "fields": {
      "user": 6,
      "email": "barbara_peters@example.com",
      "verified": true,
      "primary": true
    }
  },
  {
    "model": "account.emailaddress",
    "pk": 7,
    "fields": {
      "user": 7,
      "email": "ben_anderson@example.com",
      "verified": true,
      "primary": true
    }
  },
  {
    "model": "account.emailaddress",
    "pk": 8,
    "fields": {
      "user": 8,
      "email": "christopher_torres@example.com",
      "verified": true,
      "primary": true
    }
  },
  {
    "model": "account.emailaddress",
    "pk": 9,
    "fields": {
      "user": 9,
      "email": "colton_sanchez@example.com",
      "verified": true,
      "primary": true
    }
  },
  {
    "model": "account.emailaddress",
    "pk": 10,
    "fields": {
      "user": 10,
      "email": "daniel_carter@example.com",
      "verified": true,
      "primary": true
    }
  },
  {
    "model": "account.emailaddress",
    "pk": 11,
    "fields": {
      "user": 11,
      "email": "jean_jackson@example.com",
      "verified": true,
      "primary": true
    }
  },
  {
    "model": "account.emailaddress",
    "pk": 12,
    "fields": {
      "user": 12,
      "email": "eileen_bell@example.com",
      "verified": true,
      "primary": true
    }
  },
  {
    "model": "account.emailaddress",
    "pk": 13,
    "fields": {
      "user": 13,
      "email": "beverley_barker@example.com",
      "verified": true,
      "primary": true
    }
  },
  {
    "model": "account.emailaddress",
    "pk": 14,
    "fields": {
      "user": 14,
      "email": "fiona_bibi@example.com",
      "verified": true,
      "primary": true
    }
  },
  {
    "model": "account.emailaddress",
    "pk": 15,
    "fields": {
      "user": 15,
      "email": "natasha_james@example.com",
      "verified": true,
      "primary": true
    }
  },
  {
    "model": "account.emailaddress",
    "pk": 16,
    "fields": {
      "user": 16,
      "email": "abdul_davis@example.com",
      "verified": true,
      "primary": true
    }
  },
  {
    "model": "account.emailaddress",
    "pk": 17,
    "fields": {
      "user": 17,
      "email": "kathleen_rice@example.com",
      "verified": true,
      "primary": true
    }
  },
  {
    "model": "account.emailaddress",
    "pk": 18,
    "fields": {
      "user": 18,
      "email": "alex_davis@example.com",
      "verified": true,
      "primary": true
    }
  },
  {
    "model": "account.emailaddress",
    "pk": 19,
    "fields": {
      "user": 19,
      "email": "kevin_ross@example.com",
      "verified": true,
      "primary": true
    }
  },
  {
    "model": "account.emailaddress",
    "pk": 20,
    "fields": {
      "user": 20,
      "email": "donna_mason@example.com",
      "verified": true,
      "primary": true
    }
  },
  {
    "model": "account.emailaddress",
    "pk": 21,
    "fields": {
      "user": 21,
      "email": "daniel_green@example.com",
      "verified": true,
      "primary": true
    }
  },
  {
    "model": "account.emailaddress",
    "pk": 22,
    "fields": {
      "user": 22,
      "email": "dorothy_simms@example.com",
      "verified": true,
      "primary": true
    }
  },
  {
    "model": "account.emailaddress",
    "pk": 23,
    "fields": {
      "user": 23,
      "email": "dylan_bailey@example.com",
      "verified": true,
      "primary": true
    }
  },
  {
    "model": "account.emailaddress",
    "pk": 24,
    "fields": {
      "user": 24,
      "email": "eleanor_adams@example.com",
      "verified": true,
      "primary": true
    }
  },
  {
    "model": "account.emailaddress",
    "pk": 25,
    "fields": {
      "user": 25,
      "email": "ella_carter@example.com",
      "verified": true,
      "primary": true
    }
  },
  {
    "model": "account.emailaddress",
    "pk": 26,
    "fields": {
      "user": 26,
      "email": "elliana_young@example.com",
      "verified": true,
      "primary": true
    }
  },
  {
    "model": "account.emailaddress",
    "pk": 27,
    "fields": {
      "user": 27,
      "email": "ezra_wright@example.com",
      "verified": true,
      "primary": true
    }
  },
  {
    "model": "account.emailaddress",
    "pk": 28,
    "fields": {
      "user": 28,
      "email": "hannah_flores@example.com",
      "verified": true,
      "primary": true
    }
  },
  {
    "model": "account.emailaddress",
    "pk": 29,
    "fields": {
      "user": 29,
      "email": "hannah_ramirez@example.com",
      "verified": true,
      "primary": true
    }
  },
  {
    "model": "account.emailaddress",
    "pk": 30,
    "fields": {
      "user": 30,
      "email": "holly_fenton@example.com",
      "verified": true,
      "primary": true
    }
  },
  {
    "model": "account.emailaddress",
    "pk": 31,
    "fields": {
      "user": 31,
      "email": "isaac_peterson@example.com",
      "verified": true,
      "primary": true
    }
  },
  {
    "model": "account.emailaddress",
    "pk": 32,
    "fields": {
      "user": 32,
      "email": "isabella_johnson@example.com",
      "verified": true,
      "primary": true
    }
  },
  {
    "model": "account.emailaddress",
    "pk": 33,
    "fields": {
      "user": 33,
      "email": "jackson_walker@example.com",
      "verified": true,
      "primary": true
    }
  },
  {
    "model": "account.emailaddress",
    "pk": 34,
    "fields": {
      "user": 34,
      "email": "jane_wong@example.com",
      "verified": true,
      "primary": true
    }
  },
  {
    "model": "account.emailaddress",
    "pk": 35,
    "fields": {
      "user": 35,
      "email": "john_allen@example.com",
      "verified": true,
      "primary": true
    }
  },
  {
    "model": "account.emailaddress",
    "pk": 36,
    "fields": {
      "user": 36,
      "email": "john_dover@example.com",
      "verified": true,
      "primary": true
    }
  },
  {
    "model": "account.emailaddress",
    "pk": 37,
    "fields": {
      "user": 37,
      "email": "josh_banks@example.com",
      "verified": true,
      "primary": true
    }
  },
  {
    "model": "account.emailaddress",
    "pk": 38,
    "fields": {
      "user": 38,
      "email": "julian_davis@example.com",
      "verified": true,
      "primary": true
    }
  },
  {
    "model": "account.emailaddress",
    "pk": 39,
    "fields": {
      "user": 39,
      "email": "landon_collins@example.com",
      "verified": true,
      "primary": true
    }
  },
  {
    "model": "account.emailaddress",
    "pk": 40,
    "fields": {
      "user": 40,
      "email": "lillian_rivera@example.com",
      "verified": true,
      "primary": true
    }
  },
  {
    "model": "account.emailaddress",
    "pk": 41,
    "fields": {
      "user": 41,
      "email": "lilly_kitts@example.com",
      "verified": true,
      "primary": true
    }
  },
  {
    "model": "account.emailaddress",
    "pk": 42,
    "fields": {
      "user": 42,
      "email": "luca_phillips@example.com",
      "verified": true,
      "primary": true
    }
  },
  {
    "model": "account.emailaddress",
    "pk": 43,
    "fields": {
      "user": 43,
      "email": "lucas_ortiz@example.com",
      "verified": true,
      "primary": true
    }
  },
  {
    "model": "account.emailaddress",
    "pk": 44,
    "fields": {
      "user": 44,
      "email": "matthew_jones@example.com",
      "verified": true,
      "primary": true
    }
  },
  {
    "model": "account.emailaddress",
    "pk": 45,
    "fields": {
      "user": 45,
      "email": "natalie_anderson@example.com",
      "verified": true,
      "primary": true
    }
  },
  {
    "model": "account.emailaddress",
    "pk": 46,
    "fields": {
      "user": 46,
      "email": "nathan_stewart@example.com",
      "verified": true,
      "primary": true
    }
  },
  {
    "model": "account.emailaddress",
    "pk": 47,
    "fields": {
      "user": 47,
      "email": "oliver_king@example.com",
      "verified": true,
      "primary": true
    }
  },
  {
    "model": "account.emailaddress",
    "pk": 48,
    "fields": {
      "user": 48,
      "email": "owen_green@example.com",
      "verified": true,
      "primary": true
    }
  },
  {
    "model": "account.emailaddress",
    "pk": 49,
    "fields": {
      "user": 49,
      "email": "penelope_cruz@example.com",
      "verified": true,
      "primary": true
    }
  },
  {
    "model": "account.emailaddress",
    "pk": 50,
    "fields": {
      "user": 50,
      "email": "peyton_moore@example.com",
      "verified": true,
      "primary": true
    }
  },
  {
    "model": "account.emailaddress",
    "pk": 51,
    "fields": {
      "user": 51,
      "email": "samuel_harris@example.com",
      "verified": true,
      "primary": true
    }
  },
  {
    "model": "account.emailaddress",
    "pk": 52,
    "fields": {
      "user": 52,
      "email": "sarah_garcia@example.com",
      "verified": true,
      "primary": true
    }
  },
  {
    "model": "account.emailaddress",
    "pk": 53,
    "fields": {
      "user": 53,
      "email": "sophia_johnson@example.com",
      "verified": true,
      "primary": true
    }
  },
  {
    "model": "account.emailaddress",
    "pk": 54,
    "fields": {
      "user": 54,
      "email": "sophie_evans@example.com",
      "verified": true,
      "primary": true
    }
  },
  {
    "model": "account.emailaddress",
    "pk": 55,
    "fields": {
      "user": 55,
      "email": "sophie_smith@example.com",
      "verified": true,
      "primary": true
    }
  },
  {
    "model": "account.emailaddress",
    "pk": 56,
    "fields": {
      "user": 56,
      "email": "victoria_martin@example.com",
      "verified": true,
      "primary": true
    }
  },
  {
    "model": "account.emailaddress",
    "pk": 57,
    "fields": {
      "user": 57,
      "email": "gerald_patterson@example.com",
      "verified": true,
      "primary": true
    }
  },
  {
    "model": "account.emailaddress",
    "pk": 58,
    "fields": {
      "user": 58,
      "email": "ronald_smart@example.com",
      "verified": true,
      "primary": true
    }
  },
  {
    "model": "account.emailaddress",
    "pk": 59,
    "fields": {
      "user": 59,
      "email": "mandy_green@example.com",
      "verified": true,
      "primary": true
    }
  },
  {
    "model": "account.emailaddress",
    "pk": 60,
    "fields": {
      "user": 60,
      "email": "fiona_powell@example.com",
      "verified": true,
      "primary": true
    }
  },
  {
    "model": "account.emailaddress",
    "pk": 61,
    "fields": {
      "user": 61,
      "email": "lawrence_collier@example.com",
      "verified": true,
      "primary": true
    }
  },
  {
    "model": "account.emailaddress",
    "pk": 62,
    "fields": {
      "user": 62,
      "email": "caroline_james@example.com",
      "verified": true,
      "primary": true
    }
  },
  {
    "model": "account.emailaddress",
    "pk": 63,
    "fields": {
      "user": 63,
      "email": "stephen_bradshaw@example.com",
      "verified": true,
      "primary": true
    }
  },
  {
    "model": "account.emailaddress",
    "pk": 64,
    "fields": {
      "user": 64,
      "email": "jasmine_harris@example.com",
      "verified": true,
      "primary": true
    }
  },
  {
    "model": "account.emailaddress",
    "pk": 65,
    "fields": {
      "user": 65,
      "email": "christine_archer@example.com",
      "verified": true,
      "primary": true
    }
  },
  {
    "model": "account.emailaddress",
    "pk": 66,
    "fields": {
      "user": 66,
      "email": "charlie_wood@example.com",
      "verified": true,
      "primary": true
    }
  },
  {
    "model": "account.emailaddress",
    "pk": 67,
    "fields": {
      "user": 67,
      "email": "abdul_pope@example.com",
      "verified": true,
      "primary": true
    }
  },
  {
    "model": "account.emailaddress",
    "pk": 68,
    "fields": {
      "user": 68,
      "email": "russell_thomas@example.com",
      "verified": true,
      "primary": true
    }
  },
  {
    "model": "account.emailaddress",
    "pk": 69,
    "fields": {
      "user": 69,
      "email": "kimberley_jones@example.com",
      "verified": true,
      "primary": true
    }
  },
  {
    "model": "account.emailaddress",
    "pk": 70,
    "fields": {
      "user": 70,
      "email": "jill_holloway@example.com",
      "verified": true,
      "primary": true
    }
  },
  {
    "model": "account.emailaddress",
    "pk": 71,
    "fields": {
      "user": 71,
      "email": "craig_holden@example.com",
      "verified": true,
      "primary": true
    }
  },
  {
    "model": "account.emailaddress",
    "pk": 72,
    "fields": {
      "user": 72,
      "email": "george_miles@example.com",
      "verified": true,
      "primary": true
    }
  },
  {
    "model": "account.emailaddress",
    "pk": 73,
    "fields": {
      "user": 73,
      "email": "jodie_harper@example.com",
      "verified": true,
      "primary": true
    }
  },
  {
    "model": "account.emailaddress",
    "pk": 74,
    "fields": {
      "user": 74,
      "email": "louise_patel@example.com",
      "verified": true,
      "primary": true
    }
  },
  {
    "model": "account.emailaddress",
    "pk": 75,
    "fields": {
      "user": 75,
      "email": "alan_potter@example.com",
      "verified": true,
      "primary": true
    }
  },
  {
    "model": "account.emailaddress",
    "pk": 76,
    "fields": {
      "user": 76,
      "email": "joanne_williamson@example.com",
      "verified": true,
      "primary": true
    }
  },
  {
    "model": "account.emailaddress",
    "pk": 77,
    "fields": {
      "user": 77,
      "email": "damian_davies@example.com",
      "verified": true,
      "primary": true
    }
  },
  {
    "model": "account.emailaddress",
    "pk": 78,
    "fields": {
      "user": 78,
      "email": "tracy_miller@example.com",
      "verified": true,
      "primary": true
    }
  },
  {
    "model": "account.emailaddress",
    "pk": 79,
    "fields": {
      "user": 79,
      "email": "ryan_lee@example.com",
      "verified": true,
      "primary": true
    }
  },
  {
    "model": "account.emailaddress",
    "pk": 80,
    "fields": {
      "user": 80,
      "email": "stephanie_bailey@example.com",
      "verified": true,
      "primary": true
    }
  },
  {
    "model": "account.emailaddress",
    "pk": 81,
    "fields": {
      "user": 81,
      "email": "charles_scott@example.com",
      "verified": true,
      "primary": true
    }
  },
  {
    "model": "account.emailaddress",
    "pk": 82,
    "fields": {
      "user": 82,
      "email": "michael_turner@example.com",
      "verified": true,
      "primary": true
    }
  },
  {
    "model": "account.emailaddress",
    "pk": 83,
    "fields": {
      "user": 83,
      "email": "linda_dickinson@example.com",
      "verified": true,
      "primary": true
    }
  },
  {
    "model": "account.emailaddress",
    "pk": 84,
    "fields": {
      "user": 84,
      "email": "brenda_holt@example.com",
      "verified": true,
      "primary": true
    }
  },
  {
    "model": "account.emailaddress",
    "pk": 85,
    "fields": {
      "user": 85,
      "email": "paul_smith@example.com",
      "verified": true,
      "primary": true
    }
  },
  {
    "model": "account.emailaddress",
    "pk": 86,
    "fields": {
      "user": 86,
      "email": "victor_james@example.com",
      "verified": true,
      "primary": true
    }
  },
  {
    "model": "account.emailaddress",
    "pk": 87,
    "fields": {
      "user": 87,
      "email": "marion_clements@example.com",
      "verified": true,
      "primary": true
    }
  },
  {
    "model": "account.emailaddress",
    "pk": 88,
    "fields": {
      "user": 88,
      "email": "lewis_burrows@example.com",
      "verified": true,
      "primary": true
    }
  },
  {
    "model": "account.emailaddress",
    "pk": 89,
    "fields": {
      "user": 89,
      "email": "douglas_anderson@example.com",
      "verified": true,
      "primary": true
    }
  },
  {
    "model": "account.emailaddress",
    "pk": 90,
    "fields": {
      "user": 90,
      "email": "paul_scott@example.com",
      "verified": true,
      "primary": true
    }
  },
  {
    "model": "account.emailaddress",
    "pk": 91,
    "fields": {
      "user": 91,
      "email": "jack_gould@example.com",
      "verified": true,
      "primary": true
    }
  },
  {
    "model": "account.emailaddress",
    "pk": 92,
    "fields": {
      "user": 92,
      "email": "billy_jones@example.com",
      "verified": true,
      "primary": true
    }
  },
  {
    "model": "account.emailaddress",
    "pk": 93,
    "fields": {
      "user": 93,
      "email": "kate_parry@example.com",
      "verified": true,
      "primary": true
    }
  },
  {
    "model": "account.emailaddress",
    "pk": 94,
    "fields": {
      "user": 94,
      "email": "toby_todd@example.com",
      "verified": true,
      "primary": true
    }
  },
  {
    "model": "account.emailaddress",
    "pk": 95,
    "fields": {
      "user": 95,
      "email": "nicholas_fraser@example.com",
      "verified": true,
      "primary": true
    }
  },
  {
    "model": "account.emailaddress",
    "pk": 96,
    "fields": {
      "user": 96,
      "email": "darren_richardson@example.com",
      "verified": true,
      "primary": true
    }
  },
  {
    "model": "account.emailaddress",
    "pk": 97,
    "fields": {
      "user": 97,
      "email": "alice_rhodes@example.com",
      "verified": true,
      "primary": true
    }
  },
  {
    "model": "account.emailaddress",
    "pk": 98,
    "fields": {
      "user": 98,
      "email": "gavin_collins@example.com",
      "verified": true,
      "primary": true
    }
  },
  {
    "model": "account.emailaddress",
    "pk": 99,
    "fields": {
      "user": 99,
      "email": "stewart_smith@example.com",
      "verified": true,
      "primary": true
    }
  },
  {
    "model": "account.emailaddress",
    "pk": 100,
    "fields": {
      "user": 100,
      "email": "natasha_foster@example.com",
      "verified": true,
      "primary": true
    }
  },
  {
    "model": "account.emailaddress",
    "pk": 101,
    "fields": {
      "user": 101,
      "email": "rachel_rogers@example.com",
      "verified": true,
      "primary": true
    }
  },
  {
    "model": "account.emailaddress",
    "pk": 102,
    "fields": {
      "user": 102,
      "email": "beth_ward@example.com",
      "verified": true,
      "primary": true
    }
  },
  {
    "model": "account.emailaddress",
    "pk": 103,
    "fields": {
      "user": 103,
      "email": "lewis_webster@example.com",
      "verified": true,
      "primary": true
    }
  },
  {
    "model": "account.emailaddress",
    "pk": 104,
    "fields": {
      "user": 104,
      "email": "donna_wright@example.com",
      "verified": true,
      "primary": true
    }
  },
  {
    "model": "account.emailaddress",
    "pk": 105,
    "fields": {
      "user": 105,
      "email": "chloe_robinson@example.com",
      "verified": true,
      "primary": true
    }
  },
  {
    "model": "account.emailaddress",
    "pk": 106,
    "fields": {
      "user": 106,
      "email": "teresa_hayes@example.com",
      "verified": true,
      "primary": true
    }
  },
  {
    "model": "account.emailaddress",
    "pk": 107,
    "fields": {
      "user": 107,
      "email": "jay_hartley@example.com",
      "verified": true,
      "primary": true
    }
  },
  {
    "model": "account.emailaddress",
    "pk": 108,
    "fields": {
      "user": 108,
      "email": "jeffrey_coates@example.com",
      "verified": true,
      "primary": true
    }
  },
  {
    "model": "account.emailaddress",
    "pk": 109,
    "fields": {
      "user": 109,
      "email": "mohammed_simpson@example.com",
      "verified": true,
      "primary": true
    }
  },
  {
    "model": "account.emailaddress",
    "pk": 110,
    "fields": {
      "user": 110,
      "email": "douglas_jones@example.com",
      "verified": true,
      "primary": true
    }
  },
  {
    "model": "account.emailaddress",
    "pk": 111,
    "fields": {
      "user": 111,
      "email": "pamela_price@example.com",
      "verified": true,
      "primary": true
    }
  },
  {
    "model": "account.emailaddress",
    "pk": 112,
    "fields": {
      "user": 112,
      "email": "rhys_north@example.com",
      "verified": true,
      "primary": true
    }
  },
  {
    "model": "account.emailaddress",
    "pk": 113,
    "fields": {
      "user": 113,
      "email": "joanna_harrison@example.com",
      "verified": true,
      "primary": true
    }
  },
  {
    "model": "account.emailaddress",
    "pk": 114,
    "fields": {
      "user": 114,
      "email": "roy_evans@example.com",
      "verified": true,
      "primary": true
    }
  },
  {
    "model": "account.emailaddress",
    "pk": 115,
    "fields": {
      "user": 115,
      "email": "raymond_green@example.com",
      "verified": true,
      "primary": true
    }
  },
  {
    "model": "account.emailaddress",
    "pk": 116,
    "fields": {
      "user": 116,
      "email": "kenneth_waters@example.com",
      "verified": true,
      "primary": true
    }
  },
  {
    "model": "account.emailaddress",
    "pk": 117,
    "fields": {
      "user": 117,
      "email": "jeffrey_charlton@example.com",
      "verified": true,
      "primary": true
    }
  },
  {
    "model": "account.emailaddress",
    "pk": 118,
    "fields": {
      "user": 118,
      "email": "yvonne_wilson@example.com",
      "verified": true,
      "primary": true
    }
  },
  {
    "model": "account.emailaddress",
    "pk": 119,
    "fields": {
      "user": 119,
      "email": "julie_graham@example.com",
      "verified": true,
      "primary": true
    }
  },
  {
    "model": "account.emailaddress",
    "pk": 120,
    "fields": {
      "user": 120,
      "email": "ross_jones@example.com",
      "verified": true,
      "primary": true
    }
  }
]